{
  "title": "Load Balance NTH",
  "description": "Script generator Load Balance for Mikrotik RouterOS",
  "path": "assets/js/load-balance-nth.js",
  "controlFields": [],
  "mainFields": [
    {
      "key": "isp",
      "type": "repeat",
      "templateOptions": {
        "addText": "Add ISP"
      },
      "fieldArray": {
        "fieldGroup": [
          {
            "key": "interface",
            "type": "input",
            "templateOptions": {
              "label": "ISP Interface",
              "placeholder": "ether1",
              "description": "The interface of ISP, eg `ether1` `pppoe-out1`",
              "required": true
            }
          },
          {
            "key": "gateway",
            "type": "input",
            "templateOptions": {
              "label": "ISP Gateway",
              "placeholder": "192.168.1.1",
              "description": "The gateway of ISP",
              "required": true
            }
          }
        ]
      }
    }
  ]
}
